mohamedboualamallah-0.1.3-py3.11-nspkg.pth
mohamedboualamallah/fiji_ai/__init__.py
mohamedboualamallah/fiji_ai/audio.py
mohamedboualamallah/fiji_ai/main.py
mohamedboualamallah/fiji_ai/responses.py
mohamedboualamallah/fiji_ai/transcription.py
mohamedboualamallah/fruit_ninja/__init__.py
mohamedboualamallah/fruit_ninja/main.py
mohamedboualamallah-0.1.3.dist-info/METADATA
mohamedboualamallah-0.1.3.dist-info/WHEEL
mohamedboualamallah-0.1.3.dist-info/entry_points.txt
mohamedboualamallah-0.1.3.dist-info/namespace_packages.txt
mohamedboualamallah-0.1.3.dist-info/top_level.txt
mohamedboualamallah-0.1.3.dist-info/RECORD
